novactf/__init__.py
novactf/bibtex.py
novactf/protocols.conf
novactf/protocols/__init__.py
novactf/protocols/protocol_tomoDefocus.py
novactf/protocols/protocol_tomoReconstruction.py
novactf/tests/__init__.py
novactf/tests/test_protocols_novactf.py
scipion_em_novactf-3.2.1.dist-info/LICENSE
scipion_em_novactf-3.2.1.dist-info/METADATA
scipion_em_novactf-3.2.1.dist-info/WHEEL
scipion_em_novactf-3.2.1.dist-info/entry_points.txt
scipion_em_novactf-3.2.1.dist-info/top_level.txt
scipion_em_novactf-3.2.1.dist-info/RECORD
