Metadata-Version: 2.1
Name: scipion-em-novactf
Version: 3.2.1
Summary: Plugin to use NovaCTF in Scipion
Home-page: https://github.com/scipion-em/scipion-em-novactf
Author: I2PC
Author-email: scipion@cnb.csic.es
License: UNKNOWN
Project-URL: Bug Reports, https://github.com/scipion-em/scipion-em-novactf/issues
Project-URL: Source, https://github.com/scipion-em/scipion-em-novactf/
Keywords: scipion novactf electron-microscopy cryo-em cryo-tomography subtomogram-averaging structural-biology image-processing scipion-3.0
Platform: UNKNOWN
Classifier: Development Status :: 4 - Beta
Classifier: License :: OSI Approved :: GNU General Public License v3 (GPLv3)
Classifier: Programming Language :: Python :: 3
Requires-Dist: scipion-em-tomo
Requires-Dist: scipion-em-imod
